jaraco/translate/__init__.py
jaraco/translate/__main__.py
jaraco/translate/google.py
jaraco/translate/pmxbot.py
jaraco/translate/test_google.py
jaraco.translate-3.1.0.dist-info/LICENSE
jaraco.translate-3.1.0.dist-info/METADATA
jaraco.translate-3.1.0.dist-info/WHEEL
jaraco.translate-3.1.0.dist-info/entry_points.txt
jaraco.translate-3.1.0.dist-info/top_level.txt
jaraco.translate-3.1.0.dist-info/RECORD
