Metadata-Version: 2.1
Name: jaraco.translate
Version: 3.1.0
Summary: Natural Language Translation using the Google API
Home-page: https://github.com/jaraco/jaraco.translate
Author: Jason R. Coombs
Author-email: jaraco@jaraco.com
License: UNKNOWN
Platform: UNKNOWN
Classifier: Development Status :: 5 - Production/Stable
Classifier: Intended Audience :: Developers
Classifier: License :: OSI Approved :: MIT License
Classifier: Programming Language :: Python :: 3
Classifier: Programming Language :: Python :: 3 :: Only
Requires-Python: >=3.6
Requires-Dist: requests
Provides-Extra: docs
Requires-Dist: sphinx ; extra == 'docs'
Requires-Dist: jaraco.packaging (>=8.2) ; extra == 'docs'
Requires-Dist: rst.linker (>=1.9) ; extra == 'docs'
Provides-Extra: testing
Requires-Dist: pytest (!=3.7.3,>=3.5) ; extra == 'testing'
Requires-Dist: pytest-checkdocs (>=1.2.3) ; extra == 'testing'
Requires-Dist: pytest-flake8 ; extra == 'testing'
Requires-Dist: pytest-cov ; extra == 'testing'
Requires-Dist: pytest-enabler ; extra == 'testing'
Requires-Dist: pmxbot ; extra == 'testing'
Requires-Dist: pytest-black (>=0.3.7) ; (platform_python_implementation != "PyPy") and extra == 'testing'
Requires-Dist: pytest-mypy ; (platform_python_implementation != "PyPy") and extra == 'testing'
